master_password/__init__.py
master_password/apps.py
master_password/auth.py
master_password/management/__init__.py
master_password/management/commands/__init__.py
master_password/management/commands/make_password.py
master_password/tests/__init__.py
master_password/tests/settings.py
master_password/tests/tests.py
tests/__init__.py
tests/test_chattr_django_master_password.py
chattr_django_master_password-1.1.3.dist-info/LICENSE
chattr_django_master_password-1.1.3.dist-info/METADATA
chattr_django_master_password-1.1.3.dist-info/WHEEL
chattr_django_master_password-1.1.3.dist-info/top_level.txt
chattr_django_master_password-1.1.3.dist-info/RECORD
